hello_pysatellite-0.3.1.dist-info/METADATA
hello_pysatellite-0.3.1.dist-info/WHEEL
hello_pysatellite-0.3.1.dist-info/entry_points.txt
hello_pysatellite/__init__.py
hello_pysatellite/my.py
hello_pysatellite/who.py
hello_pysatellite-0.3.1.dist-info/RECORD
