Metadata-Version: 2.1
Name: hello-pysatellite
Version: 0.3.1
Summary: The Python program I'm distributing for the first time
Author-Email: pysatellite <pysatellite@gmail.com>
License: MIT
Project-URL: Homepage, https://github.com/pySatellite/hello-pysatellite
Project-URL: Bug tracker, https://github.com/pySatellite/hello-pysatellite/issues
Requires-Python: >=3.8
